{
  "id": "22385401",
  "name": "hair-64",
  "organizationId": "6453d11c462434a35b4abe17",
  "locked": false,
  "type": "hair",
  "bodyType": "generic",
  "editable": false,
  "gender": "neutral",
  "hasApps": false,
  "iconUrl": "https://files.readyplayer.me/asset/iconUrl/22385401/1622793946-hair-64-1699880589214.png",
  "maskUrl": "https://files.readyplayer.me/asset/maskUrl/22385401/1622793946-hair-64-mask-1699880589126.png",
  "faceBlendShapes": [],
  "hairStyle": "afro_medium",
  "eyebrowStyle": "",
  "eyeStyle": "",
  "beardStyle": "",
  "glassesStyle": "",
  "lockedCategories": [],
  "iconGlow": false,
  "createdAt": "2021-02-25T16:10:14.657Z",
  "updatedAt": "2023-06-09T13:05:07.022Z",
  "isTemplate": false,
  "removeSkin": true
}