{
  "id": "9247420",
  "name": "hair-01",
  "organizationId": "6453d11c462434a35b4abe17",
  "locked": false,
  "type": "hair",
  "bodyType": "generic",
  "editable": false,
  "gender": "neutral",
  "hasApps": false,
  "iconUrl": "https://files.readyplayer.me/asset/iconUrl/9247420/1622793819-hair-01-1699880607487.png",
  "occlusionUrl": "https://files.readyplayer.me/asset/occlusionUrl/9247420/1696953578-hair-01-ao-1699880607516.jpg",
  "faceBlendShapes": [],
  "hairStyle": "ivy_league_cut",
  "eyebrowStyle": "",
  "eyeStyle": "",
  "beardStyle": "",
  "glassesStyle": "",
  "lockedCategories": [],
  "iconGlow": false,
  "createdAt": "2020-10-26T15:42:19.807Z",
  "updatedAt": "2024-03-15T11:04:16.581Z",
  "isTemplate": false,
  "removeSkin": true
}